gnosys_treeshell/__init__.py
gnosys_treeshell/configs/dev_agent_config.json
gnosys_treeshell/configs/dev_agent_shortcuts.json
gnosys_treeshell/configs/dev_agent_zone_config.json
gnosys_treeshell/configs/dev_base_config.json
gnosys_treeshell/configs/dev_base_shortcuts.json
gnosys_treeshell/configs/dev_base_zone_config.json
gnosys_treeshell/configs/dev_user_config.json
gnosys_treeshell/configs/dev_user_shortcuts.json
gnosys_treeshell/configs/dev_user_zone_config.json
gnosys_treeshell/configs/nav_config.json
gnosys_treeshell/configs/system_agent_config.json
gnosys_treeshell/configs/system_agent_shortcuts.json
gnosys_treeshell/configs/system_agent_zone_config.json
gnosys_treeshell/configs/system_base_config.json
gnosys_treeshell/configs/system_base_shortcuts.json
gnosys_treeshell/configs/system_base_zone_config.json
gnosys_treeshell/configs/system_user_config.json
gnosys_treeshell/configs/system_user_shortcuts.json
gnosys_treeshell/configs/system_user_zone_config.json
gnosys_treeshell/configs/families/system_family.json
gnosys_treeshell/configs/families/system_hud_family.json
gnosys_treeshell/families/gnosys_family.json
gnosys_treeshell/mcp_server/__init__.py
gnosys_treeshell/mcp_server/agent_server.py
gnosys_treeshell/mcp_server/user_server.py
gnosys_treeshell-0.1.3.dist-info/licenses/LICENSE
gnosys_treeshell-0.1.3.dist-info/METADATA
gnosys_treeshell-0.1.3.dist-info/WHEEL
gnosys_treeshell-0.1.3.dist-info/entry_points.txt
gnosys_treeshell-0.1.3.dist-info/top_level.txt
gnosys_treeshell-0.1.3.dist-info/RECORD
