Metadata-Version: 2.4
Name: gnosys-treeshell
Version: 0.1.3
Summary: GNOSYS TreeShell MCP - Tree-based navigation REPL for compound intelligence ecosystem
Author: TreeShell Developer
Author-email: Isaac Wright <sancovp@gmail.com>
License-Expression: LicenseRef-GPBL-1.0
Project-URL: Homepage, https://github.com/sancovp/gnosys-treeshell
Project-URL: Repository, https://github.com/sancovp/gnosys-treeshell
Project-URL: Issues, https://github.com/sancovp/gnosys-treeshell/issues
Keywords: mcp,treeshell,claude,ai,compound-intelligence
Classifier: Development Status :: 4 - Beta
Classifier: Intended Audience :: Developers
Classifier: Programming Language :: Python :: 3
Classifier: Programming Language :: Python :: 3.10
Classifier: Programming Language :: Python :: 3.11
Classifier: Programming Language :: Python :: 3.12
Requires-Python: >=3.8
License-File: LICENSE
Requires-Dist: heaven-tree-repl>=0.1.0
Requires-Dist: gnosys-strata>=1.1.0
Requires-Dist: mcp>=1.0.0
Dynamic: author
Dynamic: license-file
Dynamic: requires-python
